django_autologin/__init__.py
django_autologin/app_settings.py
django_autologin/middleware.py
django_autologin/models.py
django_autologin/utils.py
django_autologin/templatetags/__init__.py
django_autologin/templatetags/django_autologin.py
django_autologin-0.7.1.dist-info/COPYING
django_autologin-0.7.1.dist-info/METADATA
django_autologin-0.7.1.dist-info/WHEEL
django_autologin-0.7.1.dist-info/top_level.txt
django_autologin-0.7.1.dist-info/RECORD
