Metadata-Version: 2.1
Name: django-autologin
Version: 0.7.1
Summary: Token generator and processor to provide automatic login links for users
Home-page: https://chris-lamb.co.uk/projects/django-autologin
Author: Chris Lamb
Author-email: chris@chris-lamb.co.uk
License: BSD
Platform: UNKNOWN
License-File: COPYING
Requires-Dist: Django (>=1.8)
Requires-Dist: six (>=1.10)
